mfdtool/__init__.py
mfdtool/extractor.py
mfdtool/tool.py
mfdtool-0.1.1.dist-info/entry_points.txt
mfdtool-0.1.1.dist-info/WHEEL
mfdtool-0.1.1.dist-info/METADATA
mfdtool-0.1.1.dist-info/RECORD
