Metadata-Version: 2.1
Name: mfdtool
Version: 0.1.1
Summary: Convert NFC card dumps between Flipper Zero and MFD dumps
Author: Viktor Stískala
Author-email: viktor@stiskala.cz
Requires-Python: >=3.7,<4.0
Classifier: Programming Language :: Python :: 3
Classifier: Programming Language :: Python :: 3.10
Classifier: Programming Language :: Python :: 3.7
Classifier: Programming Language :: Python :: 3.8
Classifier: Programming Language :: Python :: 3.9
Requires-Dist: bitstring (>=4.0.1,<5.0.0)
Requires-Dist: click (>=8.1.3,<9.0.0)
